inecocores/__init__.py
inecocores/core.py
inecocores-0.2.1.dist-info/LICENSE
inecocores-0.2.1.dist-info/METADATA
inecocores-0.2.1.dist-info/WHEEL
inecocores-0.2.1.dist-info/top_level.txt
inecocores-0.2.1.dist-info/RECORD
