Metadata-Version: 2.1
Name: inecocores
Version: 0.2.1
Summary: Public INECO method
Author-email: Tititab Srisookco <k.pop@ineco.co.th>
License: MIT License        
Project-URL: Homepage, https://github.com/thitithup/inecocores.git
Project-URL: Bug Tracker, https://github.com/thitithup/inecocores/issues
Classifier: Programming Language :: Python :: 3
Classifier: License :: OSI Approved :: MIT License
Classifier: Operating System :: OS Independent
Requires-Python: >=3.7
License-File: LICENSE
